README.txt
setup.py
./djangowsgiconfig/__init__.py
djangowsgiconfig.egg-info/PKG-INFO
djangowsgiconfig.egg-info/SOURCES.txt
djangowsgiconfig.egg-info/dependency_links.txt
djangowsgiconfig.egg-info/entry_points.txt
djangowsgiconfig.egg-info/requires.txt
djangowsgiconfig.egg-info/top_level.txt