Metadata-Version: 1.0
Name: djangowsgiconfig
Version: 0.1.1
Summary: a buildout recipe to create apache vhost config based on djangorecipe settings
Home-page: UNKNOWN
Author: Marco Bazzani
Author-email: pypi@marcobazzani.name
License: MIT
Platform: UNKNOWN
